klipz/__init__.py
klipz/klipz.py
klipz-0.2.4.dist-info/LICENSE
klipz-0.2.4.dist-info/METADATA
klipz-0.2.4.dist-info/WHEEL
klipz-0.2.4.dist-info/entry_points.txt
klipz-0.2.4.dist-info/top_level.txt
klipz-0.2.4.dist-info/RECORD
